tictactoelibrary/Board.py
tictactoelibrary/__init__.py
tictactoelibrary-0.0.2.dist-info/LICENSE.txt
tictactoelibrary-0.0.2.dist-info/METADATA
tictactoelibrary-0.0.2.dist-info/WHEEL
tictactoelibrary-0.0.2.dist-info/top_level.txt
tictactoelibrary-0.0.2.dist-info/RECORD
