Metadata-Version: 2.1
Name: tictactoelibrary
Version: 0.0.2
Summary: Python Tic-Tac-Toe Library.
Home-page: https://github.com/your-username/your-repo
Author: Amos Xiao
Author-email: AmosXiao1000020@proton.me
Requires-Python: >=3.10
License-File: LICENSE.txt
